{
  "displayName": "Forestry Alerts",
  "description": "Alerts for All Forestry Events.",
  "compatibleVersion": "3.7.0",
  "author": "SoggyBurrito",
  "category": "SKILLING",
  "tags": [ "event" ],
  "dependsOn": [ "Woodcutting" ],
  "alert": {"type":"AlertGroup","alerts":[{"type":"ChatAlert","message":"*Rising Roots*","regexEnabled":false,"gameMessageType":"GAME_MESSAGE","enabled":true,"name":"Rising Roots Event","debounceTime":0,"randomNotifications":false,"notifications":[{"type":"Sound","path":"Rising Roots Spawned(Github)","repeatDuration":0,"gain":8,"fireWhenFocused":true,"fireWhenAFK":false,"fireWhenAFKForSeconds":5,"delayMilliseconds":0}]},{"type":"ChatAlert","message":"*Struggling Sapling*","regexEnabled":false,"gameMessageType":"GAME_MESSAGE","enabled":true,"name":"Struggling Sapling","debounceTime":0,"randomNotifications":false,"notifications":[{"type":"Sound","path":"Struggling Sapling Spawned(Github)","repeatDuration":0,"gain":6,"fireWhenFocused":true,"fireWhenAFK":false,"fireWhenAFKForSeconds":5,"delayMilliseconds":0}]},{"type":"ChatAlert","message":"*Flowering Tree*","regexEnabled":false,"gameMessageType":"GAME_MESSAGE","enabled":true,"name":"Flowering Tree Event","debounceTime":0,"randomNotifications":false,"notifications":[{"type":"Sound","path":"Pollen Event Spawned(Github)","repeatDuration":0,"gain":8,"fireWhenFocused":true,"fireWhenAFK":false,"fireWhenAFKForSeconds":5,"delayMilliseconds":0}]},{"type":"NotificationFiredAlert","message":"*Leprechaun event*","regexEnabled":false,"enabled":true,"name":"Lep Forestry","debounceTime":0,"randomNotifications":false,"notifications":[{"type":"Sound","path":"Leprechaun Spawned(Github)","repeatDuration":0,"gain":8,"fireWhenFocused":true,"fireWhenAFK":false,"fireWhenAFKForSeconds":5,"delayMilliseconds":0}]},{"type":"ChatAlert","message":"*Bee Hive event*","regexEnabled":false,"gameMessageType":"GAME_MESSAGE","enabled":true,"name":"Bee Hive","debounceTime":0,"randomNotifications":false,"notifications":[{"type":"Sound","path":"Beehive Spawned(Github)","repeatDuration":0,"gain":8,"fireWhenFocused":true,"fireWhenAFK":false,"fireWhenAFKForSeconds":5,"delayMilliseconds":0}]},{"type":"ChatAlert","message":"*Friendly Ent*","regexEnabled":false,"gameMessageType":"GAME_MESSAGE","enabled":true,"name":"Friendly Ent","debounceTime":0,"randomNotifications":false,"notifications":[{"type":"Sound","path":"Friendly Ent Spawned(Github)","repeatDuration":0,"gain":8,"fireWhenFocused":true,"fireWhenAFK":false,"fireWhenAFKForSeconds":5,"delayMilliseconds":0}]},{"type":"ChatAlert","message":"*Poachers event*","regexEnabled":false,"gameMessageType":"GAME_MESSAGE","enabled":true,"name":"Poachers","debounceTime":0,"randomNotifications":false,"notifications":[{"type":"Sound","path":"Poachers Spawned(Github)","repeatDuration":0,"gain":8,"fireWhenFocused":true,"fireWhenAFK":false,"fireWhenAFKForSeconds":5,"delayMilliseconds":0}]},{"type":"ChatAlert","message":"*Enchantment Ritual*","regexEnabled":false,"gameMessageType":"GAME_MESSAGE","enabled":true,"name":"Enchantment Ritual","debounceTime":0,"randomNotifications":false,"notifications":[{"type":"Sound","path":"Enchantment Ritual Spawned(Github)","repeatDuration":0,"gain":6,"fireWhenFocused":true,"fireWhenAFK":false,"fireWhenAFKForSeconds":5,"delayMilliseconds":0}]},{"type":"ChatAlert","message":"*Pheasant Control*","regexEnabled":false,"gameMessageType":"GAME_MESSAGE","enabled":true,"name":"Pheasant Control","debounceTime":0,"randomNotifications":false,"notifications":[{"type":"Sound","path":"Pheasant Control Spawned(Github)","repeatDuration":0,"gain":8,"fireWhenFocused":true,"fireWhenAFK":false,"fireWhenAFKForSeconds":5,"delayMilliseconds":0}]}],"enabled":true,"name":"Forestry","debounceTime":0,"randomNotifications":false}
}
