{
  "displayName": "Overgrown Relic",
  "description": "Alerts for the Overgrown Relic from Raging Echoes League.",
  "compatibleVersion": "3.5.0",
  "author": "Grynjolf",
  "category": "SKILLING",
  "tags": ["raging","echoes","league","overgrown","relic","farming"],
  "alert": {"type":"AlertGroup","alerts":[{"type":"ChatAlert","message":"The Leprechaun planted your {*}.","regexEnabled":false,"gameMessageType":"SPAM","enabled":false,"name":"Planted Seed","debounceTime":300,"randomNotifications":false,"notifications":[{"type":"TextToSpeech","gain":10,"rate":1,"voice":"GEORGE","source":"ELEVEN_LABS","elevenLabsVoiceId":"0EpJS5C2K8MHYQRNVSmB","message":"The Leprechaun planted your $1","fireWhenFocused":true,"fireWhenAFK":false,"fireWhenAFKForSeconds":5,"delayMilliseconds":0},{"type":"Overhead","displayTime":5,"message":"The Leprechaun planted your $1","fireWhenFocused":true,"fireWhenAFK":false,"fireWhenAFKForSeconds":5,"delayMilliseconds":0}]},{"type":"ChatAlert","message":"The Leprechaun couldn\u0027t find a {*} in your bank so it left the patch alone.","regexEnabled":false,"gameMessageType":"SPAM","enabled":true,"name":"No More Seeds","debounceTime":0,"randomNotifications":false,"notifications":[{"type":"TextToSpeech","gain":10,"rate":1,"voice":"GEORGE","source":"ELEVEN_LABS","elevenLabsVoiceId":"0EpJS5C2K8MHYQRNVSmB","message":"The Leprechaun ran out of $1","fireWhenFocused":true,"fireWhenAFK":false,"fireWhenAFKForSeconds":5,"delayMilliseconds":0},{"type":"Overhead","displayTime":10,"message":"The Leprechaun ran out of $1","fireWhenFocused":true,"fireWhenAFK":false,"fireWhenAFKForSeconds":5,"delayMilliseconds":0}]},{"type":"ChatAlert","message":"Botanical allows you to keep your strawberry seed.","regexEnabled":false,"gameMessageType":"SPAM","enabled":false,"name":"Kept Seed","debounceTime":0,"randomNotifications":false,"notifications":[{"type":"Overhead","displayTime":3,"message":"Overgrown saved your seed","fireWhenFocused":true,"fireWhenAFK":false,"fireWhenAFKForSeconds":5,"delayMilliseconds":0}]}],"enabled":true,"name":"Overgrown","debounceTime":0,"randomNotifications":false}
}
